oopnet/__init__.py
oopnet/elements/__init__.py
oopnet/elements/base.py
oopnet/elements/component_registry.py
oopnet/elements/network.py
oopnet/elements/network_components.py
oopnet/elements/network_map_tags.py
oopnet/elements/options_and_reporting.py
oopnet/elements/system_operation.py
oopnet/elements/water_quality.py
oopnet/graph/__init__.py
oopnet/graph/graph.py
oopnet/hydraulics/__init__.py
oopnet/plotter/__init__.py
oopnet/plotter/bokehplot.py
oopnet/plotter/pyplot.py
oopnet/reader/__init__.py
oopnet/reader/decorators.py
oopnet/reader/module_reader.py
oopnet/reader/read.py
oopnet/reader/factories/__init__.py
oopnet/reader/factories/base.py
oopnet/reader/factories/component_factory.py
oopnet/reader/factories/options_and_reporting.py
oopnet/reader/reading_modules/__init__.py
oopnet/reader/reading_modules/read_network_components.py
oopnet/reader/reading_modules/read_network_map_tags.py
oopnet/reader/reading_modules/read_options_and_reporting.py
oopnet/reader/reading_modules/read_system_operation.py
oopnet/reader/reading_modules/read_water_quality.py
oopnet/reader/unit_converter/__init__.py
oopnet/reader/unit_converter/convert.py
oopnet/report/__init__.py
oopnet/report/binaryfile_reader.py
oopnet/report/error_manager.py
oopnet/report/report.py
oopnet/report/reportfile_reader.py
oopnet/report/simulation_errors.py
oopnet/simulator/__init__.py
oopnet/simulator/epanet2.py
oopnet/simulator/runepanet.exe
oopnet/utils/__init__.py
oopnet/utils/oopnet_logging.py
oopnet/utils/timer.py
oopnet/utils/utils.py
oopnet/utils/adders/__init__.py
oopnet/utils/adders/add_element.py
oopnet/utils/getters/__init__.py
oopnet/utils/getters/element_lists.py
oopnet/utils/getters/get_by_id.py
oopnet/utils/getters/property_getters.py
oopnet/utils/getters/topology_getters.py
oopnet/utils/getters/vectors.py
oopnet/utils/removers/__init__.py
oopnet/utils/removers/remove_element.py
oopnet/writer/__init__.py
oopnet/writer/decorators.py
oopnet/writer/module_reader.py
oopnet/writer/write.py
oopnet-0.3.1.dist-info/LICENSE
oopnet-0.3.1.dist-info/METADATA
oopnet-0.3.1.dist-info/WHEEL
oopnet-0.3.1.dist-info/top_level.txt
oopnet-0.3.1.dist-info/RECORD
