Metadata-Version: 2.1
Name: oopnet
Version: 0.3.1
Summary: Object-oriented EPANET in Python
Home-page: UNKNOWN
License: MIT
Project-URL: Documentation, https://oopnet.readthedocs.io
Platform: UNKNOWN
Classifier: Development Status :: 4 - Beta
Classifier: Intended Audience :: Developers
Classifier: Topic :: Scientific/Engineering
Classifier: License :: OSI Approved :: MIT License
Classifier: Programming Language :: Python :: 3.9
Classifier: Programming Language :: Python :: 3.10
Classifier: Typing :: Typed
License-File: LICENSE
Requires-Dist: networkx
Requires-Dist: numpy
Requires-Dist: pandas
Requires-Dist: xarray
Requires-Dist: matplotlib
Requires-Dist: bokeh
